setup.py
Package_for_internship.egg-info/PKG-INFO
Package_for_internship.egg-info/SOURCES.txt
Package_for_internship.egg-info/dependency_links.txt
Package_for_internship.egg-info/top_level.txt
cmc_dataeng_internship_kenneth_paulsen/exercise13.py