Metadata-Version: 2.1
Name: Package-for-internship
Version: 0.0.1
Summary: Easy package for internship test
Author: Kenneth Paulsen
Author-email: kennethpaulsen1997@gmail.com
